qiskit_hangyul/__init__.py
qiskit_hangyul/quantier.py
qiskit_hangyul-0.5.0.dist-info/METADATA
qiskit_hangyul-0.5.0.dist-info/WHEEL
qiskit_hangyul-0.5.0.dist-info/top_level.txt
qiskit_hangyul-0.5.0.dist-info/RECORD
